drb/addons/addon.py
drb/core/__init__.py
drb/core/_version.py
drb/core/cortex_validator.py
drb/core/events.py
drb/core/factory.py
drb/core/impls.py
drb/core/item.py
drb/core/node.py
drb/core/path.py
drb/core/predicate.py
drb/core/signature.py
drb/drivers/file/__init__.py
drb/drivers/file/file.py
drb/drivers/xml/__init__.py
drb/drivers/xml/factory.py
drb/drivers/xml/node.py
drb/exceptions/core.py
drb/exceptions/file.py
drb/keyring/bitwarden/__init__.py
drb/keyring/bitwarden/bitwarden.py
drb/nodes/abstract_node.py
drb/nodes/logical_node.py
drb/nodes/mutable_node.py
drb/nodes/url_node.py
drb/signatures/core.py
drb/signatures/xquery.py
drb/topics/resolver.py
drb/topics/topic.py
drb/topics/dao/__init__.py
drb/topics/dao/manager_dao.py
drb/topics/dao/rdf_dao.py
drb/topics/dao/topic_dao.py
drb/topics/dao/topic_schema.yml
drb/topics/dao/xml_dao.py
drb/topics/dao/yaml_dao.py
drb/topics/file/__init__.py
drb/topics/file/cortex.yml
drb/topics/xml/__init__.py
drb/topics/xml/cortex.yml
drb/utils/__init__.py
drb/utils/drb_python_script.py
drb/utils/plugins.py
drb/utils/utils.py
drb/xquery/XQueryLexer.py
drb/xquery/XQueryParser.py
drb/xquery/XQueryParserListener.py
drb/xquery/XQueryParserVisitor.py
drb/xquery/__init__.py
drb/xquery/drb_xquery.py
drb/xquery/drb_xquery_cmd.py
drb/xquery/drb_xquery_context.py
drb/xquery/drb_xquery_func.py
drb/xquery/drb_xquery_item.py
drb/xquery/drb_xquery_res_to_string.py
drb/xquery/drb_xquery_utils.py
drb/xquery/drb_xquery_variable.py
drb/xquery/drb_xquery_visitor.py
drb/xquery/execptions.py
drb-2.2.2.dist-info/LICENCE.txt
drb-2.2.2.dist-info/METADATA
drb-2.2.2.dist-info/WHEEL
drb-2.2.2.dist-info/entry_points.txt
drb-2.2.2.dist-info/top_level.txt
drb-2.2.2.dist-info/RECORD
