Metadata-Version: 2.1
Name: drb
Version: 2.2.2
Summary: Data Request Broker
Author: GAEL Systems
Author-email: drb-python@gael.fr
License: LGPLv3
Classifier: Programming Language :: Python :: 3.8
Classifier: License :: OSI Approved :: GNU Lesser General Public License v3 (LGPLv3)
Requires-Python: >=3.8
License-File: LICENCE.txt
Requires-Dist: importlib-metadata >=4.11.4
Requires-Dist: jsonschema ==4.17.0
Requires-Dist: PyYaml ~=6.0.2
Requires-Dist: click ==8.1.3
Requires-Dist: keyring ~=23.13.1
Requires-Dist: requests ~=2.27.1
Requires-Dist: defusedxml >=0.7.1
Requires-Dist: Deprecated >=1.2.13
Requires-Dist: antlr4-python3-runtime ==4.9.3
Requires-Dist: python-dateutil ~=2.8.2
Requires-Dist: rdflib ~=7.0.0
